slowly/__init__.py
slowly/auth.py
slowly/client.py
slowly/errors.py
slowly/http.py
slowly/models/__init__.py
slowly/models/abc.py
slowly/models/letter.py
slowly/models/user.py
slowly/state.py
slowly/types.py
slowly_py-0.1.3.dist-info/LICENSE
slowly_py-0.1.3.dist-info/METADATA
slowly_py-0.1.3.dist-info/WHEEL
slowly_py-0.1.3.dist-info/RECORD
