Metadata-Version: 2.3
Name: slowly.py
Version: 0.1.3
Summary: Unofficial asynchronous API/Client for Slowly.
License: GPL-3.0-or-later
Author: tiagovla
Author-email: tiagovla@gmail.com
Requires-Python: >=3.13,<4.0
Classifier: License :: OSI Approved :: GNU General Public License v3 or later (GPLv3+)
Classifier: Programming Language :: Python :: 3
Classifier: Programming Language :: Python :: 3.13
Provides-Extra: docs
Requires-Dist: aiohttp (>=3.11.11,<4.0.0)
Requires-Dist: uuid (>=1.30,<2.0)
